odoo/addons/product_top_category/README.rst
odoo/addons/product_top_category/__init__.py
odoo/addons/product_top_category/__manifest__.py
odoo/addons/product_top_category/i18n/product_top_category.pot
odoo/addons/product_top_category/models/__init__.py
odoo/addons/product_top_category/models/product_category.py
odoo/addons/product_top_category/models/product_template.py
odoo/addons/product_top_category/readme/DESCRIPTION.rst
odoo/addons/product_top_category/static/description/icon.png
odoo/addons/product_top_category/static/description/index.html
odoo/addons/product_top_category/views/product_category.xml
odoo12_addon_product_top_category-12.0.1.0.1.dist-info/METADATA
odoo12_addon_product_top_category-12.0.1.0.1.dist-info/WHEEL
odoo12_addon_product_top_category-12.0.1.0.1.dist-info/top_level.txt
odoo12_addon_product_top_category-12.0.1.0.1.dist-info/RECORD
